replit/__init__.py
replit/__main__.py
replit/database/__init__.py
replit/database/database.py
replit/database/default_db.py
replit/database/server.py
replit/goval/__init__.py
replit/goval/api/__init__.py
replit/goval/api/client_pb2.py
replit/goval/api/features/__init__.py
replit/goval/api/features/features_pb2.py
replit/goval/api/repl/__init__.py
replit/goval/api/repl/repl_pb2.py
replit/goval/api/signing_pb2.py
replit/identity/__init__.py
replit/identity/exceptions.py
replit/identity/sign.py
replit/identity/verify.py
replit/info.py
replit/web/__init__.py
replit/web/app.py
replit/web/user.py
replit/web/utils.py
replit-4.1.0.dist-info/LICENSE
replit-4.1.0.dist-info/METADATA
replit-4.1.0.dist-info/WHEEL
replit-4.1.0.dist-info/entry_points.txt
replit-4.1.0.dist-info/RECORD
