Metadata-Version: 2.1
Name: replit
Version: 4.1.0
Summary: A library for interacting with features of Replit
Home-page: https://github.com/replit/replit-py
License: ISC
Author: Replit
Author-email: contact@replit.com
Requires-Python: >=3.9,<4.0
Classifier: License :: OSI Approved
Classifier: Programming Language :: Python :: 3
Classifier: Programming Language :: Python :: 3.9
Classifier: Programming Language :: Python :: 3.10
Classifier: Programming Language :: Python :: 3.11
Classifier: Programming Language :: Python :: 3.12
Requires-Dist: Flask (>=2.0.0)
Requires-Dist: Werkzeug (>=2,<4)
Requires-Dist: aiohttp (>=3.6.2)
Requires-Dist: aiohttp-retry (>=2.8.3,<3.0.0)
Requires-Dist: protobuf (>=4.21.8,<5.0.0)
Requires-Dist: pyseto (>=1.6.11,<2.0.0)
Requires-Dist: requests (>=2.25.1,<3.0.0)
Requires-Dist: typing_extensions (>=4,<5)
Requires-Dist: urllib3 (>=1.26,<3)
Project-URL: Documentation, https://replit-py.readthedocs.org/
Project-URL: Repository, https://github.com/replit/replit-py
